slanet_plus_table/__init__.py
slanet_plus_table/main.py
slanet_plus_table/setup.py
slanet_plus_table/utils.py
slanet_plus_table/models/inference.pdiparams
slanet_plus_table/models/inference.pdmodel
slanet_plus_table/table_matcher/__init__.py
slanet_plus_table/table_matcher/matcher.py
slanet_plus_table/table_matcher/utils.py
slanet_plus_table/table_structure/__init__.py
slanet_plus_table/table_structure/table_structure.py
slanet_plus_table/table_structure/utils.py
slanet_plus_table-0.0.2.dist-info/LICENSE
slanet_plus_table-0.0.2.dist-info/METADATA
slanet_plus_table-0.0.2.dist-info/WHEEL
slanet_plus_table-0.0.2.dist-info/top_level.txt
slanet_plus_table-0.0.2.dist-info/RECORD
